correction_ea_vhr/__init__.py
correction_ea_vhr/corrector.py
correction_ea_vhr/utils.py
correction_ea_vhr/model/VHR.h5
correction_ea_vhr-0.2.dist-info/METADATA
correction_ea_vhr-0.2.dist-info/WHEEL
correction_ea_vhr-0.2.dist-info/top_level.txt
correction_ea_vhr-0.2.dist-info/RECORD
