Metadata-Version: 2.4
Name: correction_ea_vhr
Version: 0.2
Summary: Neural network correction tool for activation energy in VHR thermoluminescence
Home-page: https://github.com/Eduardo-TePe/correction_ea_vhr
Author: JF Benavente & JE Tenopala
Classifier: Programming Language :: Python :: 3
Classifier: Operating System :: OS Independent
Requires-Python: >=3.7
Requires-Dist: tensorflow
Requires-Dist: numpy
Requires-Dist: pandas
Requires-Dist: openpyxl
Dynamic: author
Dynamic: classifier
Dynamic: description
Dynamic: description-content-type
Dynamic: home-page
Dynamic: requires-dist
Dynamic: requires-python
Dynamic: summary
